llm_parse_json/__init__.py
llm_parse_json/parser.py
tests/__init__.py
tests/test_parser.py
llm_parse_json-0.1.6.7.dist-info/LICENSE
llm_parse_json-0.1.6.7.dist-info/METADATA
llm_parse_json-0.1.6.7.dist-info/WHEEL
llm_parse_json-0.1.6.7.dist-info/top_level.txt
llm_parse_json-0.1.6.7.dist-info/RECORD
