Metadata-Version: 2.1
Name: llm-parse-json
Version: 0.1.6.7
Summary: A simple JSON parsing tool that preprocesses and parses JSON strings.
Home-page: https://github.com/li-xiu-qi/llm-parse-json
Author: li-xiu-qi
Author-email: lixiuqixiaoke@qq.com
Classifier: Programming Language :: Python :: 3
Classifier: License :: OSI Approved :: MIT License
Classifier: Operating System :: OS Independent
Requires-Python: >=3.6
License-File: LICENSE
